main.py
google_cse/__init__.py
google_cse/client.py
google_cse/parameters.py
google_cse/results.py
google_cse-0.1.2.dist-info/licenses/LICENSE
google_cse-0.1.2.dist-info/METADATA
google_cse-0.1.2.dist-info/WHEEL
google_cse-0.1.2.dist-info/top_level.txt
google_cse-0.1.2.dist-info/RECORD
