Metadata-Version: 2.4
Name: google-cse
Version: 0.1.2
Summary: Simple Google Custom Search Engine (CSE) wrapper.
Author-email: M Razif Rizqullah <razifrizqullah@gmail.com>
License: Apache 2.0
Project-URL: Homepage, https://github.com/rizquuula/google-cse
Project-URL: Source, https://github.com/rizquuula/google-cse
Project-URL: Issues, https://github.com/rizquuula/google-cse/issues
Requires-Python: >=3.12
License-File: LICENSE
Requires-Dist: pydantic>=2.11.7
Requires-Dist: python-dotenv>=1.1.1
Requires-Dist: requests>=2.32.5
Dynamic: license-file
